{
    "sourceFile": "resources/views/pages/public/kegiatan.blade.php",
    "activeCommit": 0,
    "commits": [
        {
            "activePatchIndex": 0,
            "patches": [
                {
                    "date": 1766408104172,
                    "content": "Index: \n===================================================================\n--- \n+++ \n"
                }
            ],
            "date": 1766408104172,
            "name": "Commit-0",
            "content": "@extends('layouts.app')\r\n\r\n@section('title', 'Kegiatan Organisasi')\r\n\r\n@section('content')\r\n    <h2>Kegiatan Organisasi</h2>\r\n    <p>Daftar kegiatan organisasi (dummy/static).</p>\r\n    <ul>\r\n        <li>Seminar Teknologi - 1 Januari</li>\r\n        <li>Latihan Kepemimpinan - 5 Februari</li>\r\n    </ul>\r\n@endsection\r\n"
        }
    ]
}